binarn/__init__.py
binarn/py.typed
binarn-0.0.3.dist-info/LICENSE
binarn-0.0.3.dist-info/WHEEL
binarn-0.0.3.dist-info/METADATA
binarn-0.0.3.dist-info/RECORD
