Metadata-Version: 2.1
Name: binarn
Version: 0.0.3
Summary: Find arbitrary keys in deep dictionaries.
Home-page: https://github.com/bfontaine/binarn
License: MIT
Author: Baptiste Fontaine
Author-email: b@ptistefontaine.fr
Requires-Python: >=3.8,<4.0
Classifier: License :: OSI Approved :: MIT License
Classifier: Programming Language :: Python :: 3
Classifier: Programming Language :: Python :: 3.10
Classifier: Programming Language :: Python :: 3.8
Classifier: Programming Language :: Python :: 3.9
